{
  "nombre": "Knockbox",
  "categoria": "Barista",
  "precio": 22999,
  "descripcion": "Knockbox para café, ideal para descartar el café usado del portafiltro de forma práctica, rápida y prolija. Su diseño permite golpear cómodamente el portafiltro sobre la barra central, ayudando a mantener limpia la zona de preparación.\n\nEs un accesorio resistente, fácil de vaciar y de limpiar, perfecto para uso diario en casa, cafeterías o espacios baristas.",
  "material": "ABS",
  "incluye": "1 knockbox",
  "imagenes": [
    "/images/productos/1-12.webp",
    "/images/productos/2-12.webp",
    "/images/productos/3-13.webp",
    "/images/productos/4-14.webp",
    "/images/productos/5-13.webp",
    "/images/productos/6-13.webp",
    "/images/productos/7-9.webp",
    "/images/productos/8-3.webp"
  ],
  "destacado": false
}